Workbook

Sheet Tableau de bord
A1: Nhill — tableau de bord commercial (90 jours) / sales dashboard
A3: Date de début (lundi S1) / Start date (Monday W1)
A5: Indicateur / Indicator | B5: Réalisé / Actual | C5: Objectif / Target | D5: Atteinte / Progress | E5: Définition
A6: Prospects identifiés | B6: =SUM(Hebdo!C2:C14) -> 0 | C6: 150 | D6: =IFERROR(B6/C6,0) -> 0 | E6: lignes ajoutées au suivi
A7: Contacts réalisés | B7: =SUM(Hebdo!D2:D14) -> 0 | C7: 90 | D7: =IFERROR(B7/C7,0) -> 0 | E7: statut ≥ contacté
A8: Démos faites | B8: =SUM(Hebdo!E2:E14) -> 0 | C8: 25 | D8: =IFERROR(B8/C8,0) -> 0 | E8: statut ≥ démo faite
A9: Taux contact → démo | B9: =IFERROR(B8/B7,0) -> 0 | C9: 0.25 | D9: =IFERROR(B9/C9,0) -> 0 | E9: démos / contacts
A10: Pilotes signés | B10: =SUM(Hebdo!F2:F14) -> 0 | C10: 10 | D10: =IFERROR(B10/C10,0) -> 0 | E10: conventions signées
A11: Taux démo → pilote | B11: =IFERROR(B10/B8,0) -> 0 | C11: 0.4 | D11: =IFERROR(B11/C11,0) -> 0 | E11: pilotes signés / démos
A12: Pilotes actifs (dernière semaine saisie) | B12: =IFERROR(LOOKUP(2,1/(Hebdo!G2:G14<>""),Hebdo!G2:G14),0) -> 0 | C12: 10 | D12: =IFERROR(B12/C12,0) -> 0 | E12: ≥ 4 jours d'usage la semaine passée
A13: Clients | B13: =SUM(Hebdo!I2:I14) -> 0 | C13: 4 | D13: =IFERROR(B13/C13,0) -> 0 | E13: premier paiement confirmé
A14: Taux pilote → client | B14: =IFERROR(B13/SUM(Hebdo!H2:H14),0) -> 0 | C14: 0.4 | D14: =IFERROR(B14/C14,0) -> 0 | E14: clients / pilotes terminés
A15: Partenaires signés | B15: =SUM(Hebdo!J2:J14) -> 0 | C15: 3 | D15: =IFERROR(B15/C15,0) -> 0 | E15: contrats signés
A16: Note de recommandation moyenne | B16: =IFERROR(AVERAGE(Hebdo!K2:K14),0) -> 0 | C16: 7 | D16: =IFERROR(B16/C16,0) -> 0 | E16: moyenne 0-10
A17: Incidents bloquants > 48 h (cumul) | B17: =SUM(Hebdo!L2:L14) -> 0 | C17: 0 | E17: doit rester à 0
A18: Dépensé (USD) | B18: =Budget!$F$16 -> 0 | C18: =Budget!$D$16 -> 295 | D18: =IFERROR(B18/C18,0) -> 0 | E18: vs enveloppe du scénario (feuille Budget)
A19: Coût par démo (USD) | B19: =IFERROR(B18/B8,0) -> 0 | E19: dépenses / démos
A21: Objectifs : plan de 90 jours (marketing/fr/03-plan-90-jours.md). Ne jamais additionner USD et CDF.
A22: Mode d'emploi : saisir la date de début ci-dessus, puis chaque lundi la ligne de la semaine dans « Hebdo » ; les dépenses dans « Budget ».

Sheet Taux
A1: Taux de change de référence / Reference exchange rate
A3: CDF pour 1 USD / CDF per 1 USD | B3: 2264
A4: Date du taux / Rate date | B4: 2026-10-26
A5: Source | B5: Banque centrale du Congo, cours officiel — https://www.bcc.cd/marche-des-changes/cours-de-change
A7: Cellules jaunes à texte bleu = à saisir. Les autres cellules sont calculées. / Yellow cells with blue text = inputs; others are formulas.

Sheet Budget
A1: Budget 90 jours — enveloppes proposées (à confirmer par devis) / 90-day budget — proposed envelopes
A2: Choix du scénario / Scenario (A ou/or B) : | C2: A
A4: Poste / Item | B4: Enveloppe A (USD) | C4: Enveloppe B (USD) | D4: Enveloppe retenue (USD) | E4: Enveloppe retenue (CDF) | F4: Dépensé (USD) | G4: Dépensé (CDF) | H4: Écart (USD) | I4: Justificatif / Receipt
A5: Forfaits de données mobiles / Mobile data | B5: 45 | C5: 60 | D5: =IF($C$2="B",C5,B5) -> 45 | E5: =D5*Taux!$B$3 -> 101880 | F5: 0 | G5: =F5*Taux!$B$3 -> 0 | H5: =D5-F5 -> 45
A6: Impression fiches et affiches / Sheets and posters | B6: 60 | C6: 60 | D6: =IF($C$2="B",C6,B6) -> 60 | E6: =D6*Taux!$B$3 -> 135840 | F6: 0 | G6: =F6*Taux!$B$3 -> 0 | H6: =D6-F6 -> 60
A7: Impression complémentaire / Extra printing | B7: 0 | C7: 150 | D7: =IF($C$2="B",C7,B7) -> 0 | E7: =D7*Taux!$B$3 -> 0 | F7: 0 | G7: =F7*Taux!$B$3 -> 0 | H7: =D7-F7 -> 0
A8: Transport | B8: 120 | C8: 250 | D8: =IF($C$2="B",C8,B8) -> 120 | E8: =D8*Taux!$B$3 -> 271680 | F8: 0 | G8: =F8*Taux!$B$3 -> 0 | H8: =D8-F8 -> 120
A9: Domaine et hébergement du site / Domain and hosting | B9: 30 | C9: 30 | D9: =IF($C$2="B",C9,B9) -> 30 | E9: =D9*Taux!$B$3 -> 67920 | F9: 0 | G9: =F9*Taux!$B$3 -> 0 | H9: =D9-F9 -> 30
A10: Séance de démonstration groupée / Group demo | B10: 40 | C10: 0 | D10: =IF($C$2="B",C10,B10) -> 40 | E10: =D10*Taux!$B$3 -> 90560 | F10: 0 | G10: =F10*Taux!$B$3 -> 0 | H10: =D10-F10 -> 40
A11: Publicité réseaux sociaux / Social-media ads | B11: 0 | C11: 300 | D11: =IF($C$2="B",C11,B11) -> 0 | E11: =D11*Taux!$B$3 -> 0 | F11: 0 | G11: =F11*Taux!$B$3 -> 0 | H11: =D11-F11 -> 0
A12: Événement d'entrepreneurs / Entrepreneurs' event | B12: 0 | C12: 200 | D12: =IF($C$2="B",C12,B12) -> 0 | E12: =D12*Taux!$B$3 -> 0 | F12: 0 | G12: =F12*Taux!$B$3 -> 0 | H12: =D12-F12 -> 0
A13: Formation des partenaires / Partner training | B13: 0 | C13: 100 | D13: =IF($C$2="B",C13,B13) -> 0 | E13: =D13*Taux!$B$3 -> 0 | F13: 0 | G13: =F13*Taux!$B$3 -> 0 | H13: =D13-F13 -> 0
A14: Micro et support vidéo / Mic and video stand | B14: 0 | C14: 80 | D14: =IF($C$2="B",C14,B14) -> 0 | E14: =D14*Taux!$B$3 -> 0 | F14: 0 | G14: =F14*Taux!$B$3 -> 0 | H14: =D14-F14 -> 0
A15: Tablette Android de démonstration / Android demo tablet | B15: 0 | C15: 150 | D15: =IF($C$2="B",C15,B15) -> 0 | E15: =D15*Taux!$B$3 -> 0 | F15: 0 | G15: =F15*Taux!$B$3 -> 0 | H15: =D15-F15 -> 0
A16: Total | B16: =SUM(B5:B15) -> 295 | C16: =SUM(C5:C15) -> 1380 | D16: =SUM(D5:D15) -> 295 | E16: =SUM(E5:E15) -> 667880 | F16: =SUM(F5:F15) -> 0 | G16: =SUM(G5:G15) -> 0 | H16: =SUM(H5:H15) -> 295
A18: Taux utilisé : feuille « Taux » (BCC). Enveloppes = propositions du plan de 90 jours, pas des prix relevés.

Sheet Hebdo
A1: Semaine / Week | B1: Lundi / Monday | C1: Prospects ajoutés / added | D1: Contacts | E1: Démos faites / done | F1: Pilotes signés / signed | G1: Pilotes actifs / active | H1: Pilotes terminés / completed | I1: Clients | J1: Partenaires signés / signed | K1: Note recommandation moy. / avg score | L1: Incidents bloquants > 48 h
A2: S1 | B2: =IF('Tableau de bord'!$B$3="","",'Tableau de bord'!$B$3+0)
A3: S2 | B3: =IF('Tableau de bord'!$B$3="","",'Tableau de bord'!$B$3+7)
A4: S3 | B4: =IF('Tableau de bord'!$B$3="","",'Tableau de bord'!$B$3+14)
A5: S4 | B5: =IF('Tableau de bord'!$B$3="","",'Tableau de bord'!$B$3+21)
A6: S5 | B6: =IF('Tableau de bord'!$B$3="","",'Tableau de bord'!$B$3+28)
A7: S6 | B7: =IF('Tableau de bord'!$B$3="","",'Tableau de bord'!$B$3+35)
A8: S7 | B8: =IF('Tableau de bord'!$B$3="","",'Tableau de bord'!$B$3+42)
A9: S8 | B9: =IF('Tableau de bord'!$B$3="","",'Tableau de bord'!$B$3+49)
A10: S9 | B10: =IF('Tableau de bord'!$B$3="","",'Tableau de bord'!$B$3+56)
A11: S10 | B11: =IF('Tableau de bord'!$B$3="","",'Tableau de bord'!$B$3+63)
A12: S11 | B12: =IF('Tableau de bord'!$B$3="","",'Tableau de bord'!$B$3+70)
A13: S12 | B13: =IF('Tableau de bord'!$B$3="","",'Tableau de bord'!$B$3+77)
A14: S13 | B14: =IF('Tableau de bord'!$B$3="","",'Tableau de bord'!$B$3+84)
A16: Saisir les nombres de la semaine (pas les cumuls) ; « Pilotes actifs », « Note » et « Incidents » = valeur de la semaine.

Sheet Prospects
A1: id | B1: date_entree / entry_date | C1: etablissement / business | D1: secteur / sector | E1: commune | F1: contact_nom / contact_name | G1: contact_role | H1: telephone / phone | I1: email | J1: consentement_canal / consent_channel | K1: consentement_date / consent_date | L1: source | M1: score | N1: statut / status | O1: derniere_action / last_action | P1: prochaine_action / next_action | Q1: date_prochaine_action / next_action_date | R1: motif_perte / loss_reason | S1: notes
A2: P-0001 | B2: 2026-11-03 | C2: EXEMPLE — Boutique fictive (démo) | D2: détail | E2: Limete | F2: Exemple Nom | G2: propriétaire | J2: WhatsApp | K2: 2026-11-03 | L2: terrain | M2: 15 | N2: démo fixée | O2: visite | P2: démonstration | Q2: 2026-11-06 | S2: ligne d'exemple à supprimer

Sheet Partenaires
A1: id | B1: nom / name | C1: type | D1: commune | E1: date_contrat / contract_date | F1: prospects_enregistres / prospects_recorded | G1: demos | H1: pilotes / pilots | I1: clients / customers | J1: encaisse_usd / collected_usd | K1: commission_due_usd | L1: commission_payee_usd / commission_paid_usd | M1: derniere_rencontre / last_meeting | N1: notes
A2: PA-01 | B2: EXEMPLE — Partenaire fictif | C2: intégrateur | D2: Gombe | E2: 2026-11-10 | F2: 4 | G2: 2 | H2: 1 | I2: 0 | J2: 0 | K2: 0 | L2: 0 | M2: 2026-11-24 | N2: ligne d'exemple à supprimer
